LICENSE
MANIFEST.in
README.md
pyproject.toml
setup.py
example/example0_InvNufft.py
example/example1_TvSense.py
test/test_TvSense_LBFGS.py
test/test_TvSense_SGD.py
torchfinufft_ryan.egg-info/PKG-INFO
torchfinufft_ryan.egg-info/SOURCES.txt
torchfinufft_ryan.egg-info/dependency_links.txt
torchfinufft_ryan.egg-info/requires.txt
torchfinufft_ryan.egg-info/top_level.txt
torchfinufft_src/DirKspLoss.py
torchfinufft_src/Nufft.py
torchfinufft_src/ToeKspLoss.py
torchfinufft_src/__init__.py
torchfinufft_src/utility/__init__.py
torchfinufft_src/utility/cfft/__init__.py
torchfinufft_src/utility/cfft/main.py
torchfinufft_src/utility/ndimshow/__init__.py
torchfinufft_src/utility/ndimshow/main.py