Metadata-Version: 2.4
Name: torchfinufft-ryan
Version: 1.2.1
Summary: NUFFT module for PyTorch.
Author-email: Ryan <ryan_shanghaitech@proton.me>
License-Expression: MIT
Project-URL: Repository, https://github.com/RyanShanghaitech/torchfinufft
Project-URL: Examples, https://github.com/RyanShanghaitech/torchfinufft/tree/main/example
Keywords: NUFFT,Toeplitz,non-Carteisan,mri,PyTorch
License-File: LICENSE
Requires-Dist: numpy
Requires-Dist: torch
Requires-Dist: finufft
Dynamic: license-file
